setup.py
micropython_mlx90615.egg-info/PKG-INFO
micropython_mlx90615.egg-info/SOURCES.txt
micropython_mlx90615.egg-info/dependency_links.txt
micropython_mlx90615.egg-info/top_level.txt
mlx90615/__init__.py
mlx90615/crc8.py
mlx90615/mlx90615.py
mlx90615/examples/example0.py