Metadata-Version: 1.2
Name: micropython-mlx90615
Version: 1.2
Summary: Micropython scripts for use MLX90615 temperatures sensors.
Home-page: http://yeisoncardona.com/
Author: Yeison Cardona
Author-email: yeisoneng@gmail.com
Maintainer: Yeison Cardona
Maintainer-email: yeisoneng@gmail.com
License: GNU GPL
Download-URL: https://bitbucket.org/espressoide/micropython-mlx90615/downloads/
Platform: UNKNOWN
